Workbook

Sheet Fechamentos do ano
A1: Fechamentos Demo
A6: Fechamentos Mensais | C6: Gastos Extras | F6: Reserva de Emergencia | G6: Caixinha Revolut | H6: Renda Fixa Brasil | J6: Envios Brasil
J7: Data | K7: Valor Euros | L7: Valor Reais | M7: Cotaçao-Taxas | O7: Tirados da reserva
A8: Janeiro | B8: =JANEIRO!J7 -> 701.95 | C8: Carro | D8: -908 | F8: 1500 | G8: 250 | H8: 5000 | J8: 45330 | K8: 290.76 | L8: 1851.78 | M8: =L8/K8 -> 6.3687577 | O8: Removido | Q8: Recolocados
A9: Fevereiro | B9: =FEVEREIRO!J7 -> 389.87 | C9: Medico | D9: -480 | F9: 1580 | G9: 300 | J9: 45420 | K9: 310 | L9: 1965.86 | M9: =L9/K9 -> 6.3414839
A10: Março | B10: =MARÇ0!J7 -> 492.48 | F10: 1660 | G10: 380 | H10: 5200 | J10: 45506 | K10: 296.95 | L10: 1876.98 | M10: =L10/K10 -> 6.3208621
A11: Abril | B11: =ABRIL!J7 -> 654.13 | F11: 1740 | G11: 430 | J11: 45570 | K11: 289.04 | L11: 1900.65 | M11: =L11/K11 -> 6.5757335
A12: Maio | B12: =MAIO!J7 -> 370.67 | F12: 1820 | G12: 510 | J12: 45630 | K12: 310 | L12: 1987.23 | M12: =L12/K12 -> 6.4104194
A13: Junho | B13: =JUNHO!J7 -> 501.77 | F13: 1900 | G13: 590 | H13: 5400
A14: Julho | B14: =JULHO!J7 -> 489.18 | F14: 1980 | G14: 640
A15: Agosto | B15: =AGOSTO!J7 -> 106.5 | F15: 2060 | G15: 720
A16: Setembro | B16: =SETEMBRO!J7 -> 394.01 | F16: 2140 | G16: 770 | H16: 5600 | O16: Total | P16: =SUM(O9:O15) -> 0 | Q16: Total | R16: =SUM(Q9:Q15) -> 0
A17: Outubro | B17: =OUTUBRO!J7 -> 107.25 | F17: 2220 | G17: 850
A18: Novembro | B18: =NOVEMBRO!J7 -> 589.19 | F18: 2300 | G18: 900 | O18: A Recolocar | P18: =(P16-R16) -> 0
A19: Dezembro | B19: =DEZEMBRO!J7 -> 167.03 | D19: =SUM(D8:D18) -> -1388 | F19: 2400 | G19: 1000 | H19: 5850 | J19: Total: | K19: =SUM(K8:K18) -> 1496.75 | L19: =SUM(L8:L18) -> 9582.5
A20: Total: | B20: =SUM(B8:D8:D19) -> 2188.03
J21: Cotaçao media | K21: =MEDIAN(M8:M18) -> 6.3687577

Sheet JANEIRO
B2: ORÇAMENTO PESSOAL MENSAL
B5: RENDA MENSAL PREVISTA | C5: Salario | E5: 2100 | G5: SALDO PREVISTO | J5: =E7-J29 -> 132.51
C6: Entradas | E6: 0 | G6: (renda menos custo previso)
C7: Renda Mensal Total | E7: =SUM(E5:E6) -> 2100 | G7: SALDO REAL | J7: =E11-J31 -> 701.95
G8: (renda menos custo real)
B9: RENDA MENSAL REAL | C9: Salario | E9: 2100 | G9: DIFERENÇA | J9: =J7-J5 -> 569.44
C10: Entradas | E10: 200 | G10: (real menos previsto)
C11: Renda Mensal Total | E11: =SUM(E9:E10) -> 2300 | L11: Tipo de Gasto | M11: Total Real
L12: GASTOS FIXOS | M12: =D22 -> 758.54
L13: TRANSPORTE | M13: =D28 -> 65.32
B14: GASTOS FIXOS | C14: Custo Previsto | D14: Custo Real | E14: Diferença | G14: ENTRETENIMENTO | H14: Custo Previsto | I14: Custo Real | J14: Diferença | L14: MERCADO | M14: =D31 -> 243.55
B15: Aluguel | C15: 625 | D15: 625 | E15: =C15-D15 -> 0 | G15: Gastos pessoais | H15: 70 | I15: 50.73 | J15: =H15-I15 -> 19.27 | L15: BRASIL | M15: =D34 -> 0
B16: Telefone | C16: 20 | D16: 19.27 | E16: =C16-D16 -> 0.73 | G16: Lazer | H16: 70 | I16: 69.91 | J16: =H16-I16 -> 0.09 | L16: ENTRETENIMENTO | M16: =I19 -> 240.64
B17: Conta de Luz | C17: 50 | D17: 41.78 | E17: =C17-D17 -> 8.22 | G17: Outros | H17: 0 | I17: 45 | J17: =H17-I17 -> -45 | L17: INVESTIMENTOS | M17: =I27 -> 290
B18: Conta Conjunta Ananada | C18: 20 | D18: 20 | E18: =C18-D18 -> 0 | G18: Presentes (quando tiver) | H18: 0 | I18: 75 | J18: =H18-I18 -> -75
B19: Internet | C19: 12.5 | D19: 12.5 | E19: =C19-D19 -> 0 | G19: Subtotal | H19: =SUM(H15:H18) -> 140 | I19: =SUM(I15:I18) -> 240.64 | J19: =SUM(J15:J18) -> -100.64
B20: Academia | C20: 37 | D20: 37 | E20: =C20-D20 -> 0 | L20: Tipo de gasto | M20: Valor(€)
B21: Apple | C21: 2.99 | D21: 2.99 | E21: =C21-D21 -> 0 | G21: POUPANÇAS OU INVESTIMENTOS | H21: Custo previsto | I21: Custo Real | J21: Diferença | L21: BRASIL | M21: =_xlfn.XLOOKUP(L21,L12:L17,M12:M17,"nao encontrado") -> 0
B22: Subtotal | C22: =SUM(C15:C21) -> 767.49 | D22: =SUM(D15:D21) -> 758.54 | E22: =SUM(E15:E21) -> 8.95 | G22: Binance | H22: 50 | I22: 50 | J22: =H22-I22 -> 0
G23: IBKR | H23: 130 | I23: 0 | J23: =H23-I23 -> 130
B24: TRANSPORTE | C24: Custo Previsto | D24: Custo Real | E24: Diferença | G24: Doação | H24: 10 | I24: 10 | J24: =H24-I24 -> 0
B25: Onibus | C25: 80 | D25: 65.32 | E25: =C25-D25 -> 14.68 | G25: Apartamento (euro) | H25: 150 | I25: 150 | J25: =H25-I25 -> 0
B26: Taxi | C26: 0 | D26: 0 | E26: =C26-D26 -> 0 | G26: Reserva de emergencia (min) | H26: 80 | I26: 80 | J26: =H26-I26 -> 0
B27: Outros | C27: 0 | D27: 0 | E27: =C27-D27 -> 0 | G27: Subtotal | H27: =SUM(H22:H26) -> 420 | I27: =SUM(I22:I26) -> 290 | J27: =SUM(J22:J26) -> 130
B28: Subtotal | C28: =SUM(C25:C27) -> 80 | D28: =SUM(D25:D27) -> 65.32 | E28: =SUM(E25:E27) -> 14.68
G29: CUSTO TOTAL PREVISTO | J29: =SUM(C22+C28+C31+C34+H19+H27) -> 1967.49
B30: MERCADO/DELIVERY | C30: Custo Previsto | D30: Custo Real | E30: Diferença
B31: Mercadpo/Delivery | C31: 250 | D31: 243.55 | E31: =C31-D31 -> 6.45 | G31: CUSTO TOTAL REAL | J31: =SUM(D22+D28+D31+D34+I27+I19) -> 1598.05
B33: ENVIOS PARA O BRASIL | C33: Custo Previsto | D33: Custo Real | E33: Diferença | G33: DIFERENÇA TOTAL | J33: =J29-J31 -> 369.44
B34: Envios para o Brasil | C34: 310 | D34: 0 | E34: =C34-D34 -> 310

Sheet FEVEREIRO
B2: ORÇAMENTO PESSOAL MENSAL
B5: RENDA MENSAL PREVISTA | C5: Salario | E5: 2100 | G5: SALDO PREVISTO | J5: =E7-J29 -> 132.51
C6: Entradas | E6: 0 | G6: (renda menos custo previso)
C7: Renda Mensal Total | E7: =SUM(E5:E6) -> 2100 | G7: SALDO REAL | J7: =E11-J31 -> 389.87
G8: (renda menos custo real)
B9: RENDA MENSAL REAL | C9: Salario | E9: 2100 | G9: DIFERENÇA | J9: =J7-J5 -> 257.36
C10: Entradas | E10: 200 | G10: (real menos previsto)
C11: Renda Mensal Total | E11: =SUM(E9:E10) -> 2300 | L11: Tipo de Gasto | M11: Total Real
L12: GASTOS FIXOS | M12: =D22 -> 760.48
L13: TRANSPORTE | M13: =D28 -> 88.67
B14: GASTOS FIXOS | C14: Custo Previsto | D14: Custo Real | E14: Diferença | G14: ENTRETENIMENTO | H14: Custo Previsto | I14: Custo Real | J14: Diferença | L14: MERCADO | M14: =D31 -> 235.51
B15: Aluguel | C15: 625 | D15: 625 | E15: =C15-D15 -> 0 | G15: Gastos pessoais | H15: 70 | I15: 80.34 | J15: =H15-I15 -> -10.34 | L15: BRASIL | M15: =D34 -> 290.76
B16: Telefone | C16: 20 | D16: 20.66 | E16: =C16-D16 -> -0.66 | G16: Lazer | H16: 70 | I16: 94.37 | J16: =H16-I16 -> -24.37 | L16: ENTRETENIMENTO | M16: =I19 -> 174.71
B17: Conta de Luz | C17: 50 | D17: 42.33 | E17: =C17-D17 -> 7.67 | G17: Outros | H17: 0 | I17: 0 | J17: =H17-I17 -> 0 | L17: INVESTIMENTOS | M17: =I27 -> 360
B18: Conta Conjunta Ananada | C18: 20 | D18: 20 | E18: =C18-D18 -> 0 | G18: Presentes (quando tiver) | H18: 0 | I18: 0 | J18: =H18-I18 -> 0
B19: Internet | C19: 12.5 | D19: 12.5 | E19: =C19-D19 -> 0 | G19: Subtotal | H19: =SUM(H15:H18) -> 140 | I19: =SUM(I15:I18) -> 174.71 | J19: =SUM(J15:J18) -> -34.71
B20: Academia | C20: 37 | D20: 37 | E20: =C20-D20 -> 0 | L20: Tipo de gasto | M20: Valor(€)
B21: Apple | C21: 2.99 | D21: 2.99 | E21: =C21-D21 -> 0 | G21: POUPANÇAS OU INVESTIMENTOS | H21: Custo previsto | I21: Custo Real | J21: Diferença | L21: BRASIL | M21: =_xlfn.XLOOKUP(L21,L12:L17,M12:M17,"nao encontrado") -> 290.76
B22: Subtotal | C22: =SUM(C15:C21) -> 767.49 | D22: =SUM(D15:D21) -> 760.48 | E22: =SUM(E15:E21) -> 7.01 | G22: Binance | H22: 50 | I22: 0 | J22: =H22-I22 -> 50
G23: IBKR | H23: 130 | I23: 130 | J23: =H23-I23 -> 0
B24: TRANSPORTE | C24: Custo Previsto | D24: Custo Real | E24: Diferença | G24: Doação | H24: 10 | I24: 0 | J24: =H24-I24 -> 10
B25: Onibus | C25: 80 | D25: 78.67 | E25: =C25-D25 -> 1.33 | G25: Apartamento (euro) | H25: 150 | I25: 150 | J25: =H25-I25 -> 0
B26: Taxi | C26: 0 | D26: 0 | E26: =C26-D26 -> 0 | G26: Reserva de emergencia (min) | H26: 80 | I26: 80 | J26: =H26-I26 -> 0
B27: Outros | C27: 0 | D27: 10 | E27: =C27-D27 -> -10 | G27: Subtotal | H27: =SUM(H22:H26) -> 420 | I27: =SUM(I22:I26) -> 360 | J27: =SUM(J22:J26) -> 60
B28: Subtotal | C28: =SUM(C25:C27) -> 80 | D28: =SUM(D25:D27) -> 88.67 | E28: =SUM(E25:E27) -> -8.67
G29: CUSTO TOTAL PREVISTO | J29: =SUM(C22+C28+C31+C34+H19+H27) -> 1967.49
B30: MERCADO/DELIVERY | C30: Custo Previsto | D30: Custo Real | E30: Diferença
B31: Mercadpo/Delivery | C31: 250 | D31: 235.51 | E31: =C31-D31 -> 14.49 | G31: CUSTO TOTAL REAL | J31: =SUM(D22+D28+D31+D34+I27+I19) -> 1910.13
B33: ENVIOS PARA O BRASIL | C33: Custo Previsto | D33: Custo Real | E33: Diferença | G33: DIFERENÇA TOTAL | J33: =J29-J31 -> 57.36
B34: Envios para o Brasil | C34: 310 | D34: 290.76 | E34: =C34-D34 -> 19.24

Sheet MARÇ0
B2: ORÇAMENTO PESSOAL MENSAL
B5: RENDA MENSAL PREVISTA | C5: Salario | E5: 2100 | G5: SALDO PREVISTO | J5: =E7-J29 -> 132.51
C6: Entradas | E6: 0 | G6: (renda menos custo previso)
C7: Renda Mensal Total | E7: =SUM(E5:E6) -> 2100 | G7: SALDO REAL | J7: =E11-J31 -> 492.48
G8: (renda menos custo real)
B9: RENDA MENSAL REAL | C9: Salario | E9: 2100 | G9: DIFERENÇA | J9: =J7-J5 -> 359.97
C10: Entradas | E10: 150 | G10: (real menos previsto)
C11: Renda Mensal Total | E11: =SUM(E9:E10) -> 2250 | L11: Tipo de Gasto | M11: Total Real
L12: GASTOS FIXOS | M12: =D22 -> 765.49
L13: TRANSPORTE | M13: =D28 -> 135.2
B14: GASTOS FIXOS | C14: Custo Previsto | D14: Custo Real | E14: Diferença | G14: ENTRETENIMENTO | H14: Custo Previsto | I14: Custo Real | J14: Diferença | L14: MERCADO | M14: =D31 -> 229.8
B15: Aluguel | C15: 625 | D15: 625 | E15: =C15-D15 -> 0 | G15: Gastos pessoais | H15: 70 | I15: 88.45 | J15: =H15-I15 -> -18.45 | L15: BRASIL | M15: =D34 -> 0
B16: Telefone | C16: 20 | D16: 19.31 | E16: =C16-D16 -> 0.69 | G16: Lazer | H16: 70 | I16: 53.58 | J16: =H16-I16 -> 16.42 | L16: ENTRETENIMENTO | M16: =I19 -> 217.03
B17: Conta de Luz | C17: 50 | D17: 48.69 | E17: =C17-D17 -> 1.31 | G17: Outros | H17: 0 | I17: 0 | J17: =H17-I17 -> 0 | L17: INVESTIMENTOS | M17: =I27 -> 410
B18: Conta Conjunta Ananada | C18: 20 | D18: 20 | E18: =C18-D18 -> 0 | G18: Presentes (quando tiver) | H18: 0 | I18: 75 | J18: =H18-I18 -> -75
B19: Internet | C19: 12.5 | D19: 12.5 | E19: =C19-D19 -> 0 | G19: Subtotal | H19: =SUM(H15:H18) -> 140 | I19: =SUM(I15:I18) -> 217.03 | J19: =SUM(J15:J18) -> -77.03
B20: Academia | C20: 37 | D20: 37 | E20: =C20-D20 -> 0 | L20: Tipo de gasto | M20: Valor(€)
B21: Apple | C21: 2.99 | D21: 2.99 | E21: =C21-D21 -> 0 | G21: POUPANÇAS OU INVESTIMENTOS | H21: Custo previsto | I21: Custo Real | J21: Diferença | L21: BRASIL | M21: =_xlfn.XLOOKUP(L21,L12:L17,M12:M17,"nao encontrado") -> 0
B22: Subtotal | C22: =SUM(C15:C21) -> 767.49 | D22: =SUM(D15:D21) -> 765.49 | E22: =SUM(E15:E21) -> 2 | G22: Binance | H22: 50 | I22: 50 | J22: =H22-I22 -> 0
G23: IBKR | H23: 130 | I23: 130 | J23: =H23-I23 -> 0
B24: TRANSPORTE | C24: Custo Previsto | D24: Custo Real | E24: Diferença | G24: Doação | H24: 10 | I24: 0 | J24: =H24-I24 -> 10
B25: Onibus | C25: 80 | D25: 95.2 | E25: =C25-D25 -> -15.2 | G25: Apartamento (euro) | H25: 150 | I25: 150 | J25: =H25-I25 -> 0
B26: Taxi | C26: 0 | D26: 40 | E26: =C26-D26 -> -40 | G26: Reserva de emergencia (min) | H26: 80 | I26: 80 | J26: =H26-I26 -> 0
B27: Outros | C27: 0 | D27: 0 | E27: =C27-D27 -> 0 | G27: Subtotal | H27: =SUM(H22:H26) -> 420 | I27: =SUM(I22:I26) -> 410 | J27: =SUM(J22:J26) -> 10
B28: Subtotal | C28: =SUM(C25:C27) -> 80 | D28: =SUM(D25:D27) -> 135.2 | E28: =SUM(E25:E27) -> -55.2
G29: CUSTO TOTAL PREVISTO | J29: =SUM(C22+C28+C31+C34+H19+H27) -> 1967.49
B30: MERCADO/DELIVERY | C30: Custo Previsto | D30: Custo Real | E30: Diferença
B31: Mercadpo/Delivery | C31: 250 | D31: 229.8 | E31: =C31-D31 -> 20.2 | G31: CUSTO TOTAL REAL | J31: =SUM(D22+D28+D31+D34+I27+I19) -> 1757.52
B33: ENVIOS PARA O BRASIL | C33: Custo Previsto | D33: Custo Real | E33: Diferença | G33: DIFERENÇA TOTAL | J33: =J29-J31 -> 209.97
B34: Envios para o Brasil | C34: 310 | D34: 0 | E34: =C34-D34 -> 310

Sheet ABRIL
B2: ORÇAMENTO PESSOAL MENSAL
B5: RENDA MENSAL PREVISTA | C5: Salario | E5: 2100 | G5: SALDO PREVISTO | J5: =E7-J29 -> 132.51
C6: Entradas | E6: 0 | G6: (renda menos custo previso)
C7: Renda Mensal Total | E7: =SUM(E5:E6) -> 2100 | G7: SALDO REAL | J7: =E11-J31 -> 654.13
G8: (renda menos custo real)
B9: RENDA MENSAL REAL | C9: Salario | E9: 2100 | G9: DIFERENÇA | J9: =J7-J5 -> 521.62
C10: Entradas | E10: 150 | G10: (real menos previsto)
C11: Renda Mensal Total | E11: =SUM(E9:E10) -> 2250 | L11: Tipo de Gasto | M11: Total Real
L12: GASTOS FIXOS | M12: =D22 -> 755.99
L13: TRANSPORTE | M13: =D28 -> 80.77
B14: GASTOS FIXOS | C14: Custo Previsto | D14: Custo Real | E14: Diferença | G14: ENTRETENIMENTO | H14: Custo Previsto | I14: Custo Real | J14: Diferença | L14: MERCADO | M14: =D31 -> 300.79
B15: Aluguel | C15: 625 | D15: 625 | E15: =C15-D15 -> 0 | G15: Gastos pessoais | H15: 70 | I15: 49.99 | J15: =H15-I15 -> 20.01 | L15: BRASIL | M15: =D34 -> 0
B16: Telefone | C16: 20 | D16: 19.26 | E16: =C16-D16 -> 0.74 | G16: Lazer | H16: 70 | I16: 93.33 | J16: =H16-I16 -> -23.33 | L16: ENTRETENIMENTO | M16: =I19 -> 188.32
B17: Conta de Luz | C17: 50 | D17: 39.24 | E17: =C17-D17 -> 10.76 | G17: Outros | H17: 0 | I17: 45 | J17: =H17-I17 -> -45 | L17: INVESTIMENTOS | M17: =I27 -> 270
B18: Conta Conjunta Ananada | C18: 20 | D18: 20 | E18: =C18-D18 -> 0 | G18: Presentes (quando tiver) | H18: 0 | I18: 0 | J18: =H18-I18 -> 0
B19: Internet | C19: 12.5 | D19: 12.5 | E19: =C19-D19 -> 0 | G19: Subtotal | H19: =SUM(H15:H18) -> 140 | I19: =SUM(I15:I18) -> 188.32 | J19: =SUM(J15:J18) -> -48.32
B20: Academia | C20: 37 | D20: 37 | E20: =C20-D20 -> 0 | L20: Tipo de gasto | M20: Valor(€)
B21: Apple | C21: 2.99 | D21: 2.99 | E21: =C21-D21 -> 0 | G21: POUPANÇAS OU INVESTIMENTOS | H21: Custo previsto | I21: Custo Real | J21: Diferença | L21: BRASIL | M21: =_xlfn.XLOOKUP(L21,L12:L17,M12:M17,"nao encontrado") -> 0
B22: Subtotal | C22: =SUM(C15:C21) -> 767.49 | D22: =SUM(D15:D21) -> 755.99 | E22: =SUM(E15:E21) -> 11.5 | G22: Binance | H22: 50 | I22: 50 | J22: =H22-I22 -> 0
G23: IBKR | H23: 130 | I23: 130 | J23: =H23-I23 -> 0
B24: TRANSPORTE | C24: Custo Previsto | D24: Custo Real | E24: Diferença | G24: Doação | H24: 10 | I24: 10 | J24: =H24-I24 -> 0
B25: Onibus | C25: 80 | D25: 80.77 | E25: =C25-D25 -> -0.77 | G25: Apartamento (euro) | H25: 150 | I25: 0 | J25: =H25-I25 -> 150
B26: Taxi | C26: 0 | D26: 0 | E26: =C26-D26 -> 0 | G26: Reserva de emergencia (min) | H26: 80 | I26: 80 | J26: =H26-I26 -> 0
B27: Outros | C27: 0 | D27: 0 | E27: =C27-D27 -> 0 | G27: Subtotal | H27: =SUM(H22:H26) -> 420 | I27: =SUM(I22:I26) -> 270 | J27: =SUM(J22:J26) -> 150
B28: Subtotal | C28: =SUM(C25:C27) -> 80 | D28: =SUM(D25:D27) -> 80.77 | E28: =SUM(E25:E27) -> -0.77
G29: CUSTO TOTAL PREVISTO | J29: =SUM(C22+C28+C31+C34+H19+H27) -> 1967.49
B30: MERCADO/DELIVERY | C30: Custo Previsto | D30: Custo Real | E30: Diferença
B31: Mercadpo/Delivery | C31: 250 | D31: 300.79 | E31: =C31-D31 -> -50.79 | G31: CUSTO TOTAL REAL | J31: =SUM(D22+D28+D31+D34+I27+I19) -> 1595.87
B33: ENVIOS PARA O BRASIL | C33: Custo Previsto | D33: Custo Real | E33: Diferença | G33: DIFERENÇA TOTAL | J33: =J29-J31 -> 371.62
B34: Envios para o Brasil | C34: 310 | D34: 0 | E34: =C34-D34 -> 310

Sheet MAIO
B2: ORÇAMENTO PESSOAL MENSAL
B5: RENDA MENSAL PREVISTA | C5: Salario | E5: 2100 | G5: SALDO PREVISTO | J5: =E7-J29 -> 132.51
C6: Entradas | E6: 0 | G6: (renda menos custo previso)
C7: Renda Mensal Total | E7: =SUM(E5:E6) -> 2100 | G7: SALDO REAL | J7: =E11-J31 -> 370.67
G8: (renda menos custo real)
B9: RENDA MENSAL REAL | C9: Salario | E9: 2100 | G9: DIFERENÇA | J9: =J7-J5 -> 238.16
C10: Entradas | E10: 200 | G10: (real menos previsto)
C11: Renda Mensal Total | E11: =SUM(E9:E10) -> 2300 | L11: Tipo de Gasto | M11: Total Real
L12: GASTOS FIXOS | M12: =D22 -> 762.31
L13: TRANSPORTE | M13: =D28 -> 105.86
B14: GASTOS FIXOS | C14: Custo Previsto | D14: Custo Real | E14: Diferença | G14: ENTRETENIMENTO | H14: Custo Previsto | I14: Custo Real | J14: Diferença | L14: MERCADO | M14: =D31 -> 229.99
B15: Aluguel | C15: 625 | D15: 625 | E15: =C15-D15 -> 0 | G15: Gastos pessoais | H15: 70 | I15: 87.96 | J15: =H15-I15 -> -17.96 | L15: BRASIL | M15: =D34 -> 310
B16: Telefone | C16: 20 | D16: 20.51 | E16: =C16-D16 -> -0.51 | G16: Lazer | H16: 70 | I16: 78.21 | J16: =H16-I16 -> -8.21 | L16: ENTRETENIMENTO | M16: =I19 -> 181.17
B17: Conta de Luz | C17: 50 | D17: 44.31 | E17: =C17-D17 -> 5.69 | G17: Outros | H17: 0 | I17: 15 | J17: =H17-I17 -> -15 | L17: INVESTIMENTOS | M17: =I27 -> 340
B18: Conta Conjunta Ananada | C18: 20 | D18: 20 | E18: =C18-D18 -> 0 | G18: Presentes (quando tiver) | H18: 0 | I18: 0 | J18: =H18-I18 -> 0
B19: Internet | C19: 12.5 | D19: 12.5 | E19: =C19-D19 -> 0 | G19: Subtotal | H19: =SUM(H15:H18) -> 140 | I19: =SUM(I15:I18) -> 181.17 | J19: =SUM(J15:J18) -> -41.17
B20: Academia | C20: 37 | D20: 37 | E20: =C20-D20 -> 0 | L20: Tipo de gasto | M20: Valor(€)
B21: Apple | C21: 2.99 | D21: 2.99 | E21: =C21-D21 -> 0 | G21: POUPANÇAS OU INVESTIMENTOS | H21: Custo previsto | I21: Custo Real | J21: Diferença | L21: BRASIL | M21: =_xlfn.XLOOKUP(L21,L12:L17,M12:M17,"nao encontrado") -> 310
B22: Subtotal | C22: =SUM(C15:C21) -> 767.49 | D22: =SUM(D15:D21) -> 762.31 | E22: =SUM(E15:E21) -> 5.18 | G22: Binance | H22: 50 | I22: 50 | J22: =H22-I22 -> 0
G23: IBKR | H23: 130 | I23: 130 | J23: =H23-I23 -> 0
B24: TRANSPORTE | C24: Custo Previsto | D24: Custo Real | E24: Diferença | G24: Doação | H24: 10 | I24: 10 | J24: =H24-I24 -> 0
B25: Onibus | C25: 80 | D25: 65.86 | E25: =C25-D25 -> 14.14 | G25: Apartamento (euro) | H25: 150 | I25: 150 | J25: =H25-I25 -> 0
B26: Taxi | C26: 0 | D26: 40 | E26: =C26-D26 -> -40 | G26: Reserva de emergencia (min) | H26: 80 | I26: 0 | J26: =H26-I26 -> 80
B27: Outros | C27: 0 | D27: 0 | E27: =C27-D27 -> 0 | G27: Subtotal | H27: =SUM(H22:H26) -> 420 | I27: =SUM(I22:I26) -> 340 | J27: =SUM(J22:J26) -> 80
B28: Subtotal | C28: =SUM(C25:C27) -> 80 | D28: =SUM(D25:D27) -> 105.86 | E28: =SUM(E25:E27) -> -25.86
G29: CUSTO TOTAL PREVISTO | J29: =SUM(C22+C28+C31+C34+H19+H27) -> 1967.49
B30: MERCADO/DELIVERY | C30: Custo Previsto | D30: Custo Real | E30: Diferença
B31: Mercadpo/Delivery | C31: 250 | D31: 229.99 | E31: =C31-D31 -> 20.01 | G31: CUSTO TOTAL REAL | J31: =SUM(D22+D28+D31+D34+I27+I19) -> 1929.33
B33: ENVIOS PARA O BRASIL | C33: Custo Previsto | D33: Custo Real | E33: Diferença | G33: DIFERENÇA TOTAL | J33: =J29-J31 -> 38.16
B34: Envios para o Brasil | C34: 310 | D34: 310 | E34: =C34-D34 -> 0

Sheet JUNHO
B2: ORÇAMENTO PESSOAL MENSAL
B5: RENDA MENSAL PREVISTA | C5: Salario | E5: 2100 | G5: SALDO PREVISTO | J5: =E7-J29 -> 132.51
C6: Entradas | E6: 0 | G6: (renda menos custo previso)
C7: Renda Mensal Total | E7: =SUM(E5:E6) -> 2100 | G7: SALDO REAL | J7: =E11-J31 -> 501.77
G8: (renda menos custo real)
B9: RENDA MENSAL REAL | C9: Salario | E9: 2100 | G9: DIFERENÇA | J9: =J7-J5 -> 369.26
C10: Entradas | E10: 100 | G10: (real menos previsto)
C11: Renda Mensal Total | E11: =SUM(E9:E10) -> 2200 | L11: Tipo de Gasto | M11: Total Real
L12: GASTOS FIXOS | M12: =D22 -> 770.53
L13: TRANSPORTE | M13: =D28 -> 86.34
B14: GASTOS FIXOS | C14: Custo Previsto | D14: Custo Real | E14: Diferença | G14: ENTRETENIMENTO | H14: Custo Previsto | I14: Custo Real | J14: Diferença | L14: MERCADO | M14: =D31 -> 232.82
B15: Aluguel | C15: 625 | D15: 625 | E15: =C15-D15 -> 0 | G15: Gastos pessoais | H15: 70 | I15: 79.12 | J15: =H15-I15 -> -9.12 | L15: BRASIL | M15: =D34 -> 0
B16: Telefone | C16: 20 | D16: 19.64 | E16: =C16-D16 -> 0.36 | G16: Lazer | H16: 70 | I16: 89.42 | J16: =H16-I16 -> -19.42 | L16: ENTRETENIMENTO | M16: =I19 -> 268.54
B17: Conta de Luz | C17: 50 | D17: 53.4 | E17: =C17-D17 -> -3.4 | G17: Outros | H17: 0 | I17: 0 | J17: =H17-I17 -> 0 | L17: INVESTIMENTOS | M17: =I27 -> 340
B18: Conta Conjunta Ananada | C18: 20 | D18: 20 | E18: =C18-D18 -> 0 | G18: Presentes (quando tiver) | H18: 0 | I18: 100 | J18: =H18-I18 -> -100
B19: Internet | C19: 12.5 | D19: 12.5 | E19: =C19-D19 -> 0 | G19: Subtotal | H19: =SUM(H15:H18) -> 140 | I19: =SUM(I15:I18) -> 268.54 | J19: =SUM(J15:J18) -> -128.54
B20: Academia | C20: 37 | D20: 37 | E20: =C20-D20 -> 0 | L20: Tipo de gasto | M20: Valor(€)
B21: Apple | C21: 2.99 | D21: 2.99 | E21: =C21-D21 -> 0 | G21: POUPANÇAS OU INVESTIMENTOS | H21: Custo previsto | I21: Custo Real | J21: Diferença | L21: BRASIL | M21: =_xlfn.XLOOKUP(L21,L12:L17,M12:M17,"nao encontrado") -> 0
B22: Subtotal | C22: =SUM(C15:C21) -> 767.49 | D22: =SUM(D15:D21) -> 770.53 | E22: =SUM(E15:E21) -> -3.04 | G22: Binance | H22: 50 | I22: 50 | J22: =H22-I22 -> 0
G23: IBKR | H23: 130 | I23: 130 | J23: =H23-I23 -> 0
B24: TRANSPORTE | C24: Custo Previsto | D24: Custo Real | E24: Diferença | G24: Doação | H24: 10 | I24: 10 | J24: =H24-I24 -> 0
B25: Onibus | C25: 80 | D25: 76.34 | E25: =C25-D25 -> 3.66 | G25: Apartamento (euro) | H25: 150 | I25: 150 | J25: =H25-I25 -> 0
B26: Taxi | C26: 0 | D26: 0 | E26: =C26-D26 -> 0 | G26: Reserva de emergencia (min) | H26: 80 | I26: 0 | J26: =H26-I26 -> 80
B27: Outros | C27: 0 | D27: 10 | E27: =C27-D27 -> -10 | G27: Subtotal | H27: =SUM(H22:H26) -> 420 | I27: =SUM(I22:I26) -> 340 | J27: =SUM(J22:J26) -> 80
B28: Subtotal | C28: =SUM(C25:C27) -> 80 | D28: =SUM(D25:D27) -> 86.34 | E28: =SUM(E25:E27) -> -6.34
G29: CUSTO TOTAL PREVISTO | J29: =SUM(C22+C28+C31+C34+H19+H27) -> 1967.49
B30: MERCADO/DELIVERY | C30: Custo Previsto | D30: Custo Real | E30: Diferença
B31: Mercadpo/Delivery | C31: 250 | D31: 232.82 | E31: =C31-D31 -> 17.18 | G31: CUSTO TOTAL REAL | J31: =SUM(D22+D28+D31+D34+I27+I19) -> 1698.23
B33: ENVIOS PARA O BRASIL | C33: Custo Previsto | D33: Custo Real | E33: Diferença | G33: DIFERENÇA TOTAL | J33: =J29-J31 -> 269.26
B34: Envios para o Brasil | C34: 310 | D34: 0 | E34: =C34-D34 -> 310

Sheet JULHO
B2: ORÇAMENTO PESSOAL MENSAL
B5: RENDA MENSAL PREVISTA | C5: Salario | E5: 2100 | G5: SALDO PREVISTO | J5: =E7-J29 -> 132.51
C6: Entradas | E6: 0 | G6: (renda menos custo previso)
C7: Renda Mensal Total | E7: =SUM(E5:E6) -> 2100 | G7: SALDO REAL | J7: =E11-J31 -> 489.18
G8: (renda menos custo real)
B9: RENDA MENSAL REAL | C9: Salario | E9: 2100 | G9: DIFERENÇA | J9: =J7-J5 -> 356.67
C10: Entradas | E10: 50 | G10: (real menos previsto)
C11: Renda Mensal Total | E11: =SUM(E9:E10) -> 2150 | L11: Tipo de Gasto | M11: Total Real
L12: GASTOS FIXOS | M12: =D22 -> 778.15
L13: TRANSPORTE | M13: =D28 -> 106.68
B14: GASTOS FIXOS | C14: Custo Previsto | D14: Custo Real | E14: Diferença | G14: ENTRETENIMENTO | H14: Custo Previsto | I14: Custo Real | J14: Diferença | L14: MERCADO | M14: =D31 -> 293.53
B15: Aluguel | C15: 625 | D15: 625 | E15: =C15-D15 -> 0 | G15: Gastos pessoais | H15: 70 | I15: 50.06 | J15: =H15-I15 -> 19.94 | L15: BRASIL | M15: =D34 -> 0
B16: Telefone | C16: 20 | D16: 19.9 | E16: =C16-D16 -> 0.1 | G16: Lazer | H16: 70 | I16: 47.4 | J16: =H16-I16 -> 22.6 | L16: ENTRETENIMENTO | M16: =I19 -> 212.46
B17: Conta de Luz | C17: 50 | D17: 60.76 | E17: =C17-D17 -> -10.76 | G17: Outros | H17: 0 | I17: 15 | J17: =H17-I17 -> -15 | L17: INVESTIMENTOS | M17: =I27 -> 270
B18: Conta Conjunta Ananada | C18: 20 | D18: 20 | E18: =C18-D18 -> 0 | G18: Presentes (quando tiver) | H18: 0 | I18: 100 | J18: =H18-I18 -> -100
B19: Internet | C19: 12.5 | D19: 12.5 | E19: =C19-D19 -> 0 | G19: Subtotal | H19: =SUM(H15:H18) -> 140 | I19: =SUM(I15:I18) -> 212.46 | J19: =SUM(J15:J18) -> -72.46
B20: Academia | C20: 37 | D20: 37 | E20: =C20-D20 -> 0 | L20: Tipo de gasto | M20: Valor(€)
B21: Apple | C21: 2.99 | D21: 2.99 | E21: =C21-D21 -> 0 | G21: POUPANÇAS OU INVESTIMENTOS | H21: Custo previsto | I21: Custo Real | J21: Diferença | L21: BRASIL | M21: =_xlfn.XLOOKUP(L21,L12:L17,M12:M17,"nao encontrado") -> 0
B22: Subtotal | C22: =SUM(C15:C21) -> 767.49 | D22: =SUM(D15:D21) -> 778.15 | E22: =SUM(E15:E21) -> -10.66 | G22: Binance | H22: 50 | I22: 50 | J22: =H22-I22 -> 0
G23: IBKR | H23: 130 | I23: 130 | J23: =H23-I23 -> 0
B24: TRANSPORTE | C24: Custo Previsto | D24: Custo Real | E24: Diferença | G24: Doação | H24: 10 | I24: 10 | J24: =H24-I24 -> 0
B25: Onibus | C25: 80 | D25: 71.68 | E25: =C25-D25 -> 8.32 | G25: Apartamento (euro) | H25: 150 | I25: 0 | J25: =H25-I25 -> 150
B26: Taxi | C26: 0 | D26: 15 | E26: =C26-D26 -> -15 | G26: Reserva de emergencia (min) | H26: 80 | I26: 80 | J26: =H26-I26 -> 0
B27: Outros | C27: 0 | D27: 20 | E27: =C27-D27 -> -20 | G27: Subtotal | H27: =SUM(H22:H26) -> 420 | I27: =SUM(I22:I26) -> 270 | J27: =SUM(J22:J26) -> 150
B28: Subtotal | C28: =SUM(C25:C27) -> 80 | D28: =SUM(D25:D27) -> 106.68 | E28: =SUM(E25:E27) -> -26.68
G29: CUSTO TOTAL PREVISTO | J29: =SUM(C22+C28+C31+C34+H19+H27) -> 1967.49
B30: MERCADO/DELIVERY | C30: Custo Previsto | D30: Custo Real | E30: Diferença
B31: Mercadpo/Delivery | C31: 250 | D31: 293.53 | E31: =C31-D31 -> -43.53 | G31: CUSTO TOTAL REAL | J31: =SUM(D22+D28+D31+D34+I27+I19) -> 1660.82
B33: ENVIOS PARA O BRASIL | C33: Custo Previsto | D33: Custo Real | E33: Diferença | G33: DIFERENÇA TOTAL | J33: =J29-J31 -> 306.67
B34: Envios para o Brasil | C34: 310 | D34: 0 | E34: =C34-D34 -> 310

Sheet AGOSTO
B2: ORÇAMENTO PESSOAL MENSAL
B5: RENDA MENSAL PREVISTA | C5: Salario | E5: 2100 | G5: SALDO PREVISTO | J5: =E7-J29 -> 132.51
C6: Entradas | E6: 0 | G6: (renda menos custo previso)
C7: Renda Mensal Total | E7: =SUM(E5:E6) -> 2100 | G7: SALDO REAL | J7: =E11-J31 -> 106.5
G8: (renda menos custo real)
B9: RENDA MENSAL REAL | C9: Salario | E9: 2100 | G9: DIFERENÇA | J9: =J7-J5 -> -26.01
C10: Entradas | E10: 50 | G10: (real menos previsto)
C11: Renda Mensal Total | E11: =SUM(E9:E10) -> 2150 | L11: Tipo de Gasto | M11: Total Real
L12: GASTOS FIXOS | M12: =D22 -> 773.78
L13: TRANSPORTE | M13: =D28 -> 140.45
B14: GASTOS FIXOS | C14: Custo Previsto | D14: Custo Real | E14: Diferença | G14: ENTRETENIMENTO | H14: Custo Previsto | I14: Custo Real | J14: Diferença | L14: MERCADO | M14: =D31 -> 267.02
B15: Aluguel | C15: 625 | D15: 625 | E15: =C15-D15 -> 0 | G15: Gastos pessoais | H15: 70 | I15: 55.3 | J15: =H15-I15 -> 14.7 | L15: BRASIL | M15: =D34 -> 296.95
B16: Telefone | C16: 20 | D16: 19.93 | E16: =C16-D16 -> 0.07 | G16: Lazer | H16: 70 | I16: 75 | J16: =H16-I16 -> -5 | L16: ENTRETENIMENTO | M16: =I19 -> 145.3
B17: Conta de Luz | C17: 50 | D17: 56.36 | E17: =C17-D17 -> -6.36 | G17: Outros | H17: 0 | I17: 15 | J17: =H17-I17 -> -15 | L17: INVESTIMENTOS | M17: =I27 -> 420
B18: Conta Conjunta Ananada | C18: 20 | D18: 20 | E18: =C18-D18 -> 0 | G18: Presentes (quando tiver) | H18: 0 | I18: 0 | J18: =H18-I18 -> 0
B19: Internet | C19: 12.5 | D19: 12.5 | E19: =C19-D19 -> 0 | G19: Subtotal | H19: =SUM(H15:H18) -> 140 | I19: =SUM(I15:I18) -> 145.3 | J19: =SUM(J15:J18) -> -5.3
B20: Academia | C20: 37 | D20: 37 | E20: =C20-D20 -> 0 | L20: Tipo de gasto | M20: Valor(€)
B21: Apple | C21: 2.99 | D21: 2.99 | E21: =C21-D21 -> 0 | G21: POUPANÇAS OU INVESTIMENTOS | H21: Custo previsto | I21: Custo Real | J21: Diferença | L21: BRASIL | M21: =_xlfn.XLOOKUP(L21,L12:L17,M12:M17,"nao encontrado") -> 296.95
B22: Subtotal | C22: =SUM(C15:C21) -> 767.49 | D22: =SUM(D15:D21) -> 773.78 | E22: =SUM(E15:E21) -> -6.29 | G22: Binance | H22: 50 | I22: 50 | J22: =H22-I22 -> 0
G23: IBKR | H23: 130 | I23: 130 | J23: =H23-I23 -> 0
B24: TRANSPORTE | C24: Custo Previsto | D24: Custo Real | E24: Diferença | G24: Doação | H24: 10 | I24: 10 | J24: =H24-I24 -> 0
B25: Onibus | C25: 80 | D25: 90.45 | E25: =C25-D25 -> -10.45 | G25: Apartamento (euro) | H25: 150 | I25: 150 | J25: =H25-I25 -> 0
B26: Taxi | C26: 0 | D26: 40 | E26: =C26-D26 -> -40 | G26: Reserva de emergencia (min) | H26: 80 | I26: 80 | J26: =H26-I26 -> 0
B27: Outros | C27: 0 | D27: 10 | E27: =C27-D27 -> -10 | G27: Subtotal | H27: =SUM(H22:H26) -> 420 | I27: =SUM(I22:I26) -> 420 | J27: =SUM(J22:J26) -> 0
B28: Subtotal | C28: =SUM(C25:C27) -> 80 | D28: =SUM(D25:D27) -> 140.45 | E28: =SUM(E25:E27) -> -60.45
G29: CUSTO TOTAL PREVISTO | J29: =SUM(C22+C28+C31+C34+H19+H27) -> 1967.49
B30: MERCADO/DELIVERY | C30: Custo Previsto | D30: Custo Real | E30: Diferença
B31: Mercadpo/Delivery | C31: 250 | D31: 267.02 | E31: =C31-D31 -> -17.02 | G31: CUSTO TOTAL REAL | J31: =SUM(D22+D28+D31+D34+I27+I19) -> 2043.5
B33: ENVIOS PARA O BRASIL | C33: Custo Previsto | D33: Custo Real | E33: Diferença | G33: DIFERENÇA TOTAL | J33: =J29-J31 -> -76.01
B34: Envios para o Brasil | C34: 310 | D34: 296.95 | E34: =C34-D34 -> 13.05

Sheet SETEMBRO
B2: ORÇAMENTO PESSOAL MENSAL
B5: RENDA MENSAL PREVISTA | C5: Salario | E5: 2100 | G5: SALDO PREVISTO | J5: =E7-J29 -> 132.51
C6: Entradas | E6: 0 | G6: (renda menos custo previso)
C7: Renda Mensal Total | E7: =SUM(E5:E6) -> 2100 | G7: SALDO REAL | J7: =E11-J31 -> 394.01
G8: (renda menos custo real)
B9: RENDA MENSAL REAL | C9: Salario | E9: 2100 | G9: DIFERENÇA | J9: =J7-J5 -> 261.5
C10: Entradas | E10: 100 | G10: (real menos previsto)
C11: Renda Mensal Total | E11: =SUM(E9:E10) -> 2200 | L11: Tipo de Gasto | M11: Total Real
L12: GASTOS FIXOS | M12: =D22 -> 754.35
L13: TRANSPORTE | M13: =D28 -> 106.75
B14: GASTOS FIXOS | C14: Custo Previsto | D14: Custo Real | E14: Diferença | G14: ENTRETENIMENTO | H14: Custo Previsto | I14: Custo Real | J14: Diferença | L14: MERCADO | M14: =D31 -> 307.99
B15: Aluguel | C15: 625 | D15: 625 | E15: =C15-D15 -> 0 | G15: Gastos pessoais | H15: 70 | I15: 75.43 | J15: =H15-I15 -> -5.43 | L15: BRASIL | M15: =D34 -> 0
B16: Telefone | C16: 20 | D16: 19.13 | E16: =C16-D16 -> 0.87 | G16: Lazer | H16: 70 | I16: 46.47 | J16: =H16-I16 -> 23.53 | L16: ENTRETENIMENTO | M16: =I19 -> 216.9
B17: Conta de Luz | C17: 50 | D17: 37.73 | E17: =C17-D17 -> 12.27 | G17: Outros | H17: 0 | I17: 45 | J17: =H17-I17 -> -45 | L17: INVESTIMENTOS | M17: =I27 -> 420
B18: Conta Conjunta Ananada | C18: 20 | D18: 20 | E18: =C18-D18 -> 0 | G18: Presentes (quando tiver) | H18: 0 | I18: 50 | J18: =H18-I18 -> -50
B19: Internet | C19: 12.5 | D19: 12.5 | E19: =C19-D19 -> 0 | G19: Subtotal | H19: =SUM(H15:H18) -> 140 | I19: =SUM(I15:I18) -> 216.9 | J19: =SUM(J15:J18) -> -76.9
B20: Academia | C20: 37 | D20: 37 | E20: =C20-D20 -> 0 | L20: Tipo de gasto | M20: Valor(€)
B21: Apple | C21: 2.99 | D21: 2.99 | E21: =C21-D21 -> 0 | G21: POUPANÇAS OU INVESTIMENTOS | H21: Custo previsto | I21: Custo Real | J21: Diferença | L21: BRASIL | M21: =_xlfn.XLOOKUP(L21,L12:L17,M12:M17,"nao encontrado") -> 0
B22: Subtotal | C22: =SUM(C15:C21) -> 767.49 | D22: =SUM(D15:D21) -> 754.35 | E22: =SUM(E15:E21) -> 13.14 | G22: Binance | H22: 50 | I22: 50 | J22: =H22-I22 -> 0
G23: IBKR | H23: 130 | I23: 130 | J23: =H23-I23 -> 0
B24: TRANSPORTE | C24: Custo Previsto | D24: Custo Real | E24: Diferença | G24: Doação | H24: 10 | I24: 10 | J24: =H24-I24 -> 0
B25: Onibus | C25: 80 | D25: 81.75 | E25: =C25-D25 -> -1.75 | G25: Apartamento (euro) | H25: 150 | I25: 150 | J25: =H25-I25 -> 0
B26: Taxi | C26: 0 | D26: 25 | E26: =C26-D26 -> -25 | G26: Reserva de emergencia (min) | H26: 80 | I26: 80 | J26: =H26-I26 -> 0
B27: Outros | C27: 0 | D27: 0 | E27: =C27-D27 -> 0 | G27: Subtotal | H27: =SUM(H22:H26) -> 420 | I27: =SUM(I22:I26) -> 420 | J27: =SUM(J22:J26) -> 0
B28: Subtotal | C28: =SUM(C25:C27) -> 80 | D28: =SUM(D25:D27) -> 106.75 | E28: =SUM(E25:E27) -> -26.75
G29: CUSTO TOTAL PREVISTO | J29: =SUM(C22+C28+C31+C34+H19+H27) -> 1967.49
B30: MERCADO/DELIVERY | C30: Custo Previsto | D30: Custo Real | E30: Diferença
B31: Mercadpo/Delivery | C31: 250 | D31: 307.99 | E31: =C31-D31 -> -57.99 | G31: CUSTO TOTAL REAL | J31: =SUM(D22+D28+D31+D34+I27+I19) -> 1805.99
B33: ENVIOS PARA O BRASIL | C33: Custo Previsto | D33: Custo Real | E33: Diferença | G33: DIFERENÇA TOTAL | J33: =J29-J31 -> 161.5
B34: Envios para o Brasil | C34: 310 | D34: 0 | E34: =C34-D34 -> 310

Sheet OUTUBRO
B2: ORÇAMENTO PESSOAL MENSAL
B5: RENDA MENSAL PREVISTA | C5: Salario | E5: 2100 | G5: SALDO PREVISTO | J5: =E7-J29 -> 132.51
C6: Entradas | E6: 0 | G6: (renda menos custo previso)
C7: Renda Mensal Total | E7: =SUM(E5:E6) -> 2100 | G7: SALDO REAL | J7: =E11-J31 -> 107.25
G8: (renda menos custo real)
B9: RENDA MENSAL REAL | C9: Salario | E9: 2100 | G9: DIFERENÇA | J9: =J7-J5 -> -25.26
C10: Entradas | E10: 50 | G10: (real menos previsto)
C11: Renda Mensal Total | E11: =SUM(E9:E10) -> 2150 | L11: Tipo de Gasto | M11: Total Real
L12: GASTOS FIXOS | M12: =D22 -> 765.65
L13: TRANSPORTE | M13: =D28 -> 87.42
B14: GASTOS FIXOS | C14: Custo Previsto | D14: Custo Real | E14: Diferença | G14: ENTRETENIMENTO | H14: Custo Previsto | I14: Custo Real | J14: Diferença | L14: MERCADO | M14: =D31 -> 224.82
B15: Aluguel | C15: 625 | D15: 625 | E15: =C15-D15 -> 0 | G15: Gastos pessoais | H15: 70 | I15: 55.27 | J15: =H15-I15 -> 14.73 | L15: BRASIL | M15: =D34 -> 289.04
B16: Telefone | C16: 20 | D16: 20.37 | E16: =C16-D16 -> -0.37 | G16: Lazer | H16: 70 | I16: 90.55 | J16: =H16-I16 -> -20.55 | L16: ENTRETENIMENTO | M16: =I19 -> 265.82
B17: Conta de Luz | C17: 50 | D17: 47.79 | E17: =C17-D17 -> 2.21 | G17: Outros | H17: 0 | I17: 45 | J17: =H17-I17 -> -45 | L17: INVESTIMENTOS | M17: =I27 -> 410
B18: Conta Conjunta Ananada | C18: 20 | D18: 20 | E18: =C18-D18 -> 0 | G18: Presentes (quando tiver) | H18: 0 | I18: 75 | J18: =H18-I18 -> -75
B19: Internet | C19: 12.5 | D19: 12.5 | E19: =C19-D19 -> 0 | G19: Subtotal | H19: =SUM(H15:H18) -> 140 | I19: =SUM(I15:I18) -> 265.82 | J19: =SUM(J15:J18) -> -125.82
B20: Academia | C20: 37 | D20: 37 | E20: =C20-D20 -> 0 | L20: Tipo de gasto | M20: Valor(€)
B21: Apple | C21: 2.99 | D21: 2.99 | E21: =C21-D21 -> 0 | G21: POUPANÇAS OU INVESTIMENTOS | H21: Custo previsto | I21: Custo Real | J21: Diferença | L21: BRASIL | M21: =_xlfn.XLOOKUP(L21,L12:L17,M12:M17,"nao encontrado") -> 289.04
B22: Subtotal | C22: =SUM(C15:C21) -> 767.49 | D22: =SUM(D15:D21) -> 765.65 | E22: =SUM(E15:E21) -> 1.84 | G22: Binance | H22: 50 | I22: 50 | J22: =H22-I22 -> 0
G23: IBKR | H23: 130 | I23: 130 | J23: =H23-I23 -> 0
B24: TRANSPORTE | C24: Custo Previsto | D24: Custo Real | E24: Diferença | G24: Doação | H24: 10 | I24: 0 | J24: =H24-I24 -> 10
B25: Onibus | C25: 80 | D25: 87.42 | E25: =C25-D25 -> -7.42 | G25: Apartamento (euro) | H25: 150 | I25: 150 | J25: =H25-I25 -> 0
B26: Taxi | C26: 0 | D26: 0 | E26: =C26-D26 -> 0 | G26: Reserva de emergencia (min) | H26: 80 | I26: 80 | J26: =H26-I26 -> 0
B27: Outros | C27: 0 | D27: 0 | E27: =C27-D27 -> 0 | G27: Subtotal | H27: =SUM(H22:H26) -> 420 | I27: =SUM(I22:I26) -> 410 | J27: =SUM(J22:J26) -> 10
B28: Subtotal | C28: =SUM(C25:C27) -> 80 | D28: =SUM(D25:D27) -> 87.42 | E28: =SUM(E25:E27) -> -7.42
G29: CUSTO TOTAL PREVISTO | J29: =SUM(C22+C28+C31+C34+H19+H27) -> 1967.49
B30: MERCADO/DELIVERY | C30: Custo Previsto | D30: Custo Real | E30: Diferença
B31: Mercadpo/Delivery | C31: 250 | D31: 224.82 | E31: =C31-D31 -> 25.18 | G31: CUSTO TOTAL REAL | J31: =SUM(D22+D28+D31+D34+I27+I19) -> 2042.75
B33: ENVIOS PARA O BRASIL | C33: Custo Previsto | D33: Custo Real | E33: Diferença | G33: DIFERENÇA TOTAL | J33: =J29-J31 -> -75.26
B34: Envios para o Brasil | C34: 310 | D34: 289.04 | E34: =C34-D34 -> 20.96

Sheet NOVEMBRO
B2: ORÇAMENTO PESSOAL MENSAL
B5: RENDA MENSAL PREVISTA | C5: Salario | E5: 2100 | G5: SALDO PREVISTO | J5: =E7-J29 -> 132.51
C6: Entradas | E6: 0 | G6: (renda menos custo previso)
C7: Renda Mensal Total | E7: =SUM(E5:E6) -> 2100 | G7: SALDO REAL | J7: =E11-J31 -> 589.19
G8: (renda menos custo real)
B9: RENDA MENSAL REAL | C9: Salario | E9: 2100 | G9: DIFERENÇA | J9: =J7-J5 -> 456.68
C10: Entradas | E10: 200 | G10: (real menos previsto)
C11: Renda Mensal Total | E11: =SUM(E9:E10) -> 2300 | L11: Tipo de Gasto | M11: Total Real
L12: GASTOS FIXOS | M12: =D22 -> 776.83
L13: TRANSPORTE | M13: =D28 -> 130.41
B14: GASTOS FIXOS | C14: Custo Previsto | D14: Custo Real | E14: Diferença | G14: ENTRETENIMENTO | H14: Custo Previsto | I14: Custo Real | J14: Diferença | L14: MERCADO | M14: =D31 -> 225.47
B15: Aluguel | C15: 625 | D15: 625 | E15: =C15-D15 -> 0 | G15: Gastos pessoais | H15: 70 | I15: 86.01 | J15: =H15-I15 -> -16.01 | L15: BRASIL | M15: =D34 -> 0
B16: Telefone | C16: 20 | D16: 20.56 | E16: =C16-D16 -> -0.56 | G16: Lazer | H16: 70 | I16: 42.09 | J16: =H16-I16 -> 27.91 | L16: ENTRETENIMENTO | M16: =I19 -> 158.1
B17: Conta de Luz | C17: 50 | D17: 58.78 | E17: =C17-D17 -> -8.78 | G17: Outros | H17: 0 | I17: 30 | J17: =H17-I17 -> -30 | L17: INVESTIMENTOS | M17: =I27 -> 420
B18: Conta Conjunta Ananada | C18: 20 | D18: 20 | E18: =C18-D18 -> 0 | G18: Presentes (quando tiver) | H18: 0 | I18: 0 | J18: =H18-I18 -> 0
B19: Internet | C19: 12.5 | D19: 12.5 | E19: =C19-D19 -> 0 | G19: Subtotal | H19: =SUM(H15:H18) -> 140 | I19: =SUM(I15:I18) -> 158.1 | J19: =SUM(J15:J18) -> -18.1
B20: Academia | C20: 37 | D20: 37 | E20: =C20-D20 -> 0 | L20: Tipo de gasto | M20: Valor(€)
B21: Apple | C21: 2.99 | D21: 2.99 | E21: =C21-D21 -> 0 | G21: POUPANÇAS OU INVESTIMENTOS | H21: Custo previsto | I21: Custo Real | J21: Diferença | L21: BRASIL | M21: =_xlfn.XLOOKUP(L21,L12:L17,M12:M17,"nao encontrado") -> 0
B22: Subtotal | C22: =SUM(C15:C21) -> 767.49 | D22: =SUM(D15:D21) -> 776.83 | E22: =SUM(E15:E21) -> -9.34 | G22: Binance | H22: 50 | I22: 50 | J22: =H22-I22 -> 0
G23: IBKR | H23: 130 | I23: 130 | J23: =H23-I23 -> 0
B24: TRANSPORTE | C24: Custo Previsto | D24: Custo Real | E24: Diferença | G24: Doação | H24: 10 | I24: 10 | J24: =H24-I24 -> 0
B25: Onibus | C25: 80 | D25: 95.41 | E25: =C25-D25 -> -15.41 | G25: Apartamento (euro) | H25: 150 | I25: 150 | J25: =H25-I25 -> 0
B26: Taxi | C26: 0 | D26: 25 | E26: =C26-D26 -> -25 | G26: Reserva de emergencia (min) | H26: 80 | I26: 80 | J26: =H26-I26 -> 0
B27: Outros | C27: 0 | D27: 10 | E27: =C27-D27 -> -10 | G27: Subtotal | H27: =SUM(H22:H26) -> 420 | I27: =SUM(I22:I26) -> 420 | J27: =SUM(J22:J26) -> 0
B28: Subtotal | C28: =SUM(C25:C27) -> 80 | D28: =SUM(D25:D27) -> 130.41 | E28: =SUM(E25:E27) -> -50.41
G29: CUSTO TOTAL PREVISTO | J29: =SUM(C22+C28+C31+C34+H19+H27) -> 1967.49
B30: MERCADO/DELIVERY | C30: Custo Previsto | D30: Custo Real | E30: Diferença
B31: Mercadpo/Delivery | C31: 250 | D31: 225.47 | E31: =C31-D31 -> 24.53 | G31: CUSTO TOTAL REAL | J31: =SUM(D22+D28+D31+D34+I27+I19) -> 1710.81
B33: ENVIOS PARA O BRASIL | C33: Custo Previsto | D33: Custo Real | E33: Diferença | G33: DIFERENÇA TOTAL | J33: =J29-J31 -> 256.68
B34: Envios para o Brasil | C34: 310 | D34: 0 | E34: =C34-D34 -> 310

Sheet DEZEMBRO
B2: ORÇAMENTO PESSOAL MENSAL
B5: RENDA MENSAL PREVISTA | C5: Salario | E5: 2100 | G5: SALDO PREVISTO | J5: =E7-J29 -> 132.51
C6: Entradas | E6: 0 | G6: (renda menos custo previso)
C7: Renda Mensal Total | E7: =SUM(E5:E6) -> 2100 | G7: SALDO REAL | J7: =E11-J31 -> 167.03
G8: (renda menos custo real)
B9: RENDA MENSAL REAL | C9: Salario | E9: 2100 | G9: DIFERENÇA | J9: =J7-J5 -> 34.52
C10: Entradas | E10: 50 | G10: (real menos previsto)
C11: Renda Mensal Total | E11: =SUM(E9:E10) -> 2150 | L11: Tipo de Gasto | M11: Total Real
L12: GASTOS FIXOS | M12: =D22 -> 756.76
L13: TRANSPORTE | M13: =D28 -> 108.67
B14: GASTOS FIXOS | C14: Custo Previsto | D14: Custo Real | E14: Diferença | G14: ENTRETENIMENTO | H14: Custo Previsto | I14: Custo Real | J14: Diferença | L14: MERCADO | M14: =D31 -> 308.72
B15: Aluguel | C15: 625 | D15: 625 | E15: =C15-D15 -> 0 | G15: Gastos pessoais | H15: 70 | I15: 76.86 | J15: =H15-I15 -> -6.86 | L15: BRASIL | M15: =D34 -> 310
B16: Telefone | C16: 20 | D16: 19.32 | E16: =C16-D16 -> 0.68 | G16: Lazer | H16: 70 | I16: 51.96 | J16: =H16-I16 -> 18.04 | L16: ENTRETENIMENTO | M16: =I19 -> 128.82
B17: Conta de Luz | C17: 50 | D17: 39.95 | E17: =C17-D17 -> 10.05 | G17: Outros | H17: 0 | I17: 0 | J17: =H17-I17 -> 0 | L17: INVESTIMENTOS | M17: =I27 -> 370
B18: Conta Conjunta Ananada | C18: 20 | D18: 20 | E18: =C18-D18 -> 0 | G18: Presentes (quando tiver) | H18: 0 | I18: 0 | J18: =H18-I18 -> 0
B19: Internet | C19: 12.5 | D19: 12.5 | E19: =C19-D19 -> 0 | G19: Subtotal | H19: =SUM(H15:H18) -> 140 | I19: =SUM(I15:I18) -> 128.82 | J19: =SUM(J15:J18) -> 11.18
B20: Academia | C20: 37 | D20: 37 | E20: =C20-D20 -> 0 | L20: Tipo de gasto | M20: Valor(€)
B21: Apple | C21: 2.99 | D21: 2.99 | E21: =C21-D21 -> 0 | G21: POUPANÇAS OU INVESTIMENTOS | H21: Custo previsto | I21: Custo Real | J21: Diferença | L21: BRASIL | M21: =_xlfn.XLOOKUP(L21,L12:L17,M12:M17,"nao encontrado") -> 310
B22: Subtotal | C22: =SUM(C15:C21) -> 767.49 | D22: =SUM(D15:D21) -> 756.76 | E22: =SUM(E15:E21) -> 10.73 | G22: Binance | H22: 50 | I22: 0 | J22: =H22-I22 -> 50
G23: IBKR | H23: 130 | I23: 130 | J23: =H23-I23 -> 0
B24: TRANSPORTE | C24: Custo Previsto | D24: Custo Real | E24: Diferença | G24: Doação | H24: 10 | I24: 10 | J24: =H24-I24 -> 0
B25: Onibus | C25: 80 | D25: 73.67 | E25: =C25-D25 -> 6.33 | G25: Apartamento (euro) | H25: 150 | I25: 150 | J25: =H25-I25 -> 0
B26: Taxi | C26: 0 | D26: 25 | E26: =C26-D26 -> -25 | G26: Reserva de emergencia (min) | H26: 80 | I26: 80 | J26: =H26-I26 -> 0
B27: Outros | C27: 0 | D27: 10 | E27: =C27-D27 -> -10 | G27: Subtotal | H27: =SUM(H22:H26) -> 420 | I27: =SUM(I22:I26) -> 370 | J27: =SUM(J22:J26) -> 50
B28: Subtotal | C28: =SUM(C25:C27) -> 80 | D28: =SUM(D25:D27) -> 108.67 | E28: =SUM(E25:E27) -> -28.67
G29: CUSTO TOTAL PREVISTO | J29: =SUM(C22+C28+C31+C34+H19+H27) -> 1967.49
B30: MERCADO/DELIVERY | C30: Custo Previsto | D30: Custo Real | E30: Diferença
B31: Mercadpo/Delivery | C31: 250 | D31: 308.72 | E31: =C31-D31 -> -58.72 | G31: CUSTO TOTAL REAL | J31: =SUM(D22+D28+D31+D34+I27+I19) -> 1982.97
B33: ENVIOS PARA O BRASIL | C33: Custo Previsto | D33: Custo Real | E33: Diferença | G33: DIFERENÇA TOTAL | J33: =J29-J31 -> -15.48
B34: Envios para o Brasil | C34: 310 | D34: 310 | E34: =C34-D34 -> 0
